skill_ovos_wolfie/LICENSE
skill_ovos_wolfie/MANIFEST.in
skill_ovos_wolfie/README.md
skill_ovos_wolfie/__init__.py
skill_ovos_wolfie/settingsmeta.json
skill_ovos_wolfie/version.py
skill_ovos_wolfie/gui/all/logo.png
skill_ovos_wolfie/gui/qt5/wolf.qml
skill_ovos_wolfie/locale/ca-es/More.voc
skill_ovos_wolfie/locale/ca-es/no_answer.dialog
skill_ovos_wolfie/locale/ca-es/search_wolfie.intent
skill_ovos_wolfie/locale/ca-es/skill.json
skill_ovos_wolfie/locale/da-dk/More.voc
skill_ovos_wolfie/locale/da-dk/no_answer.dialog
skill_ovos_wolfie/locale/da-dk/search_wolfie.intent
skill_ovos_wolfie/locale/da-dk/skill.json
skill_ovos_wolfie/locale/de-de/More.voc
skill_ovos_wolfie/locale/de-de/no_answer.dialog
skill_ovos_wolfie/locale/de-de/search_wolfie.intent
skill_ovos_wolfie/locale/de-de/skill.json
skill_ovos_wolfie/locale/en-us/MiscBlacklist.voc
skill_ovos_wolfie/locale/en-us/More.voc
skill_ovos_wolfie/locale/en-us/no_answer.dialog
skill_ovos_wolfie/locale/en-us/search_wolfie.intent
skill_ovos_wolfie/locale/en-us/skill.json
skill_ovos_wolfie/locale/es-es/More.voc
skill_ovos_wolfie/locale/es-es/no_answer.dialog
skill_ovos_wolfie/locale/es-es/search_wolfie.intent
skill_ovos_wolfie/locale/eu/More.voc
skill_ovos_wolfie/locale/eu/no_answer.dialog
skill_ovos_wolfie/locale/eu/search_wolfie.intent
skill_ovos_wolfie/locale/fr-fr/More.voc
skill_ovos_wolfie/locale/fr-fr/no_answer.dialog
skill_ovos_wolfie/locale/fr-fr/search_wolfie.intent
skill_ovos_wolfie/locale/gl-es/More.voc
skill_ovos_wolfie/locale/gl-es/no_answer.dialog
skill_ovos_wolfie/locale/gl-es/search_wolfie.intent
skill_ovos_wolfie/locale/it-it/More.voc
skill_ovos_wolfie/locale/it-it/no_answer.dialog
skill_ovos_wolfie/locale/it-it/search_wolfie.intent
skill_ovos_wolfie/locale/pt-pt/More.voc
skill_ovos_wolfie/locale/pt-pt/no_answer.dialog
skill_ovos_wolfie/locale/pt-pt/search_wolfie.intent
skill_ovos_wolfie/res/icon/wolfie.png
skill_ovos_wolfie/skill_wolfie.egg-info/PKG-INFO
skill_ovos_wolfie/skill_wolfie.egg-info/SOURCES.txt
skill_ovos_wolfie/skill_wolfie.egg-info/dependency_links.txt
skill_ovos_wolfie/skill_wolfie.egg-info/entry_points.txt
skill_ovos_wolfie/skill_wolfie.egg-info/requires.txt
skill_ovos_wolfie/skill_wolfie.egg-info/top_level.txt
skill_wolfie-0.5.3.dist-info/LICENSE
skill_wolfie-0.5.3.dist-info/METADATA
skill_wolfie-0.5.3.dist-info/WHEEL
skill_wolfie-0.5.3.dist-info/entry_points.txt
skill_wolfie-0.5.3.dist-info/top_level.txt
skill_wolfie-0.5.3.dist-info/RECORD
