Metadata-Version: 2.1
Name: skill-wolfie
Version: 0.5.3
Summary: ovos wolfram alpha skill plugin
Home-page: https://github.com/OpenVoiceOS/skill-ovos-wolfie
Author: JarbasAi
Author-email: jarbasai@mailfence.com
License: Apache-2.0
Keywords: ovos skill plugin
License-File: LICENSE
Requires-Dist: ovos-config>=0.0.12
Requires-Dist: ovos-utils>=0.7.0
Requires-Dist: ovos-workshop<4.0.0,>=3.4.0a1
Requires-Dist: ovos-wolfram-alpha-solver<1.0.0,>=0.0.2
